rst2confluence/__init__.py
rst2confluence/confluence.py
rst2jira-0.7.1.data/data/man/man1/rst2jira.1
rst2jira-0.7.1.data/scripts/rst2jira.py
rst2jira-0.7.1.dist-info/METADATA
rst2jira-0.7.1.dist-info/WHEEL
rst2jira-0.7.1.dist-info/top_level.txt
rst2jira-0.7.1.dist-info/RECORD
