Metadata-Version: 2.1
Name: rst2jira
Version: 0.7.1
Summary: reStructuredText to confluence/jira markup converter
Home-page: https://github.com/rpuntaie/rst2jira
Author: Kenichiro TANAKA
Author-email: tanaka.kenichiro@gmail.com
Maintainer: Roland Puntaier
Maintainer-email: roland.puntaier@gmail.com
License: AGPL
Platform: UNKNOWN
Classifier: Development Status :: 4 - Beta
Classifier: Environment :: Console
Classifier: License :: OSI Approved :: GNU Affero General Public License v3 or later (AGPLv3+)
Classifier: Natural Language :: English
Classifier: Operating System :: OS Independent
Classifier: Programming Language :: Python :: 3
Classifier: Intended Audience :: End Users/Desktop
Classifier: Intended Audience :: Information Technology
Classifier: Topic :: Utilities
Requires-Python: >=3.6
Requires-Dist: docutils
Requires-Dist: Pygments
